{
  "dependencies": {
    "com.vrcfury.vrcfury": {
      "version": "1.401.0"
    },
    "com.vrchat.avatars": {
      "version": "3.2.3"
    },
    "com.poiyomi.toon": {
      "version": "8.1.167"
    },
    "vrchat.blackstartx.gesture-manager": {
      "version": "3.8.6"
    },
    "com.vrchat.core.vpm-resolver": {
      "version": "0.1.23"
    }
  },
  "locked": {
    "com.vrcfury.vrcfury": {
      "version": "1.445.0",
      "dependencies": {}
    },
    "com.vrchat.avatars": {
      "version": "3.3.0",
      "dependencies": {
        "com.vrchat.base": "3.3.0"
      }
    },
    "com.vrchat.base": {
      "version": "3.3.0",
      "dependencies": {}
    },
    "com.poiyomi.toon": {
      "version": "8.1.167",
      "dependencies": {}
    },
    "vrchat.blackstartx.gesture-manager": {
      "version": "3.8.6",
      "dependencies": {
        "com.vrchat.avatars": "3.2.x || 3.3.x"
      }
    },
    "com.vrchat.core.vpm-resolver": {
      "version": "0.1.24",
      "dependencies": {}
    }
  }
}